nicesprinkler_examples/example_config.yaml
nicesprinkler_examples/example_garden.stl
nicesprinkler_examples/hose.stl
nicesprinkler_examples/nema23.stl
sprinkler/__init__.py
sprinkler/slider.py
sprinkler/sprinkler_cmd.py
sprinkler/sprinkler_config.py
sprinkler/sprinkler_core.py
sprinkler/sprinkler_head.py
sprinkler/sprinkler_sim.py
sprinkler/stepper.py
sprinkler/stepper_view.py
sprinkler/stl3d.py
sprinkler/version.py
sprinkler/waterjet.py
sprinkler/webserver.py
nicesprinkler-0.0.2.dist-info/METADATA
nicesprinkler-0.0.2.dist-info/WHEEL
nicesprinkler-0.0.2.dist-info/entry_points.txt
nicesprinkler-0.0.2.dist-info/licenses/LICENSE
nicesprinkler-0.0.2.dist-info/RECORD
