Metadata-Version: 2.4
Name: nicesprinkler
Version: 0.0.2
Summary: nicesprinkler
Project-URL: Home, https://github.com/WolfgangFahl/nicesprinkler
Project-URL: Documentation, https://wiki.bitplan.com/index.php/nicesprinkler
Project-URL: Source, https://github.com/WolfgangFahl/nicesprinkler
Author-email: Wolfgang Fahl <wf@bitplan.com>
Maintainer-email: Wolfgang Fahl <wf@bitplan.com>
License-Expression: Apache-2.0
License-File: LICENSE
Keywords: automation,lawn,nicegui,sprinkler
Classifier: Development Status :: 4 - Beta
Classifier: Environment :: Web Environment
Classifier: Intended Audience :: Developers
Classifier: Intended Audience :: Education
Classifier: Intended Audience :: Science/Research
Classifier: License :: OSI Approved :: Apache Software License
Classifier: Operating System :: OS Independent
Classifier: Programming Language :: Python :: 3 :: Only
Classifier: Programming Language :: Python :: 3.10
Classifier: Programming Language :: Python :: 3.11
Classifier: Programming Language :: Python :: 3.12
Classifier: Programming Language :: Python :: 3.13
Classifier: Topic :: Software Development :: Libraries :: Python Modules
Requires-Python: >=3.10
Requires-Dist: matplotlib>=3.9.2
Requires-Dist: ngwidgets>=0.27.1
Requires-Dist: nicegui>=2.20.0
Requires-Dist: numpy-stl>=3.1.2
Requires-Dist: pybasemkit>=0.0.3
Requires-Dist: tabulate>=0.9.0
Provides-Extra: test
Requires-Dist: green; extra == 'test'
